xamino/__init__.py
xamino/client.py
xamino/subclient.py
xamino/utilities.py
xamino-0.1.0.dist-info/LICENSE
xamino-0.1.0.dist-info/METADATA
xamino-0.1.0.dist-info/WHEEL
xamino-0.1.0.dist-info/top_level.txt
xamino-0.1.0.dist-info/RECORD
